irt/__init__.py
irt/irt.py
irt-0.0.2.dist-info/LICENSE.txt
irt-0.0.2.dist-info/METADATA
irt-0.0.2.dist-info/WHEEL
irt-0.0.2.dist-info/top_level.txt
irt-0.0.2.dist-info/RECORD
