Metadata-Version: 2.1
Name: irt
Version: 0.0.2
Summary: Item Response Theory in Python
Home-page: https://github.com/aimir/irt
Author: Amir Sarid
Author-email: aisarid@gmail.com
License: UNKNOWN
Keywords: IRT item response theory psychometrics
Platform: UNKNOWN
Requires-Dist: future
Requires-Dist: numpy
Requires-Dist: scipy
